odoo/addons/sale_limit_partner_address/__init__.py
odoo/addons/sale_limit_partner_address/__manifest__.py
odoo/addons/sale_limit_partner_address/views/sale_order_view.xml
odoo12_addon_sale_limit_partner_address-12.0.0.0.1.dist-info/METADATA
odoo12_addon_sale_limit_partner_address-12.0.0.0.1.dist-info/WHEEL
odoo12_addon_sale_limit_partner_address-12.0.0.0.1.dist-info/top_level.txt
odoo12_addon_sale_limit_partner_address-12.0.0.0.1.dist-info/RECORD
